aws_lambda_wsgi/__init__.py
aws_lambda_wsgi-0.0.5.dist-info/LICENSE
aws_lambda_wsgi-0.0.5.dist-info/METADATA
aws_lambda_wsgi-0.0.5.dist-info/WHEEL
aws_lambda_wsgi-0.0.5.dist-info/top_level.txt
aws_lambda_wsgi-0.0.5.dist-info/RECORD
