Metadata-Version: 2.1
Name: aws-lambda-wsgi
Version: 0.0.5
Summary: AWS Lambda WSGI - WSGI adapter for AWS API Gateway/Lambda Proxy Integration
Home-page: https://github.com/truckpad/aws-lambda-wsgi
Author: Marcos Araujo Sobrinho
Author-email: marcos.sobrinho@truckpad.com.br
License: UNKNOWN
Platform: UNKNOWN
Classifier: Development Status :: 2 - Pre-Alpha
Classifier: Operating System :: POSIX
Classifier: Programming Language :: Python :: 3
Classifier: Topic :: Internet :: WWW/HTTP
